modelship/__about__.py
modelship/__init__.py
modelship/__main__.py
modelship/cli.py
modelship/static/ortworker.js
modelship/static/vendor/bootstrap/bootstrap.esm.min.js
modelship/static/vendor/bootstrap-icons/bootstrap-icons.min.css
modelship/static/vendor/bootstrap-icons/fonts/bootstrap-icons.woff
modelship/static/vendor/bootstrap-icons/fonts/bootstrap-icons.woff2
modelship/static/vendor/halfmoon/halfmoon.min.css
modelship/static/vendor/halfmoon/halfmoon.modern.css
modelship/static/vendor/onnxruntime-web/ort-wasm-simd-threaded.jsep.wasm
modelship/static/vendor/onnxruntime-web/ort.bundle.min.js
modelship/templates/onnx_runtime_web.html
modelship-0.2.1.dist-info/METADATA
modelship-0.2.1.dist-info/WHEEL
modelship-0.2.1.dist-info/entry_points.txt
modelship-0.2.1.dist-info/licenses/LICENSE
modelship-0.2.1.dist-info/RECORD
