Metadata-Version: 2.4
Name: modelship
Version: 0.2.1
Summary: Ship machine learning models in minutes, not months
Project-URL: Repository, https://github.com/datalpia/modelship
Project-URL: Issues, https://github.com/datalpia/modelship/issues
Project-URL: Changelog, https://github.com/datalpia/modelship/blob/main/CHANGELOG.md
License: Apache-2.0
License-File: LICENSE
Keywords: deployment,machine-learning,onnx,webassembly
Classifier: Development Status :: 2 - Pre-Alpha
Classifier: Intended Audience :: Developers
Classifier: Intended Audience :: End Users/Desktop
Classifier: Intended Audience :: Information Technology
Classifier: Intended Audience :: Other Audience
Classifier: Intended Audience :: Science/Research
Classifier: Programming Language :: Python :: 3.10
Classifier: Programming Language :: Python :: 3.11
Classifier: Programming Language :: Python :: 3.12
Classifier: Programming Language :: Python :: 3.13
Classifier: Topic :: Scientific/Engineering :: Artificial Intelligence
Classifier: Topic :: Software Development
Classifier: Topic :: Utilities
Requires-Python: <3.14,>=3.10
Requires-Dist: jinja2>=3
Requires-Dist: onnxruntime>=1
Requires-Dist: pydantic>=2
Requires-Dist: pyyaml>=6
